packageurl/__init__.py
purl_python-0.2.1.dist-info/DESCRIPTION.rst
purl_python-0.2.1.dist-info/LICENSE.txt
purl_python-0.2.1.dist-info/METADATA
purl_python-0.2.1.dist-info/RECORD
purl_python-0.2.1.dist-info/WHEEL
purl_python-0.2.1.dist-info/metadata.json
purl_python-0.2.1.dist-info/top_level.txt
